setup.py
django_test_pep8.egg-info/PKG-INFO
django_test_pep8.egg-info/SOURCES.txt
django_test_pep8.egg-info/dependency_links.txt
django_test_pep8.egg-info/requires.txt
django_test_pep8.egg-info/top_level.txt
test_pep8/__init__.py
test_pep8/models.py
test_pep8/tests.py
test_pep8/views.py