Metadata-Version: 1.1
Name: django-test-pep8
Version: 0.1
Summary: PEP8 Tests to Django projects
Home-page: https://github.com/TracyWebTech/django-test-pep8
Author: Davi Oliveira
Author-email: UNKNOWN
License: BSD
Download-URL: https://github.com/TracyWebTech/django-test-pep8/downloads
Keywords: django test pep8
Platform: UNKNOWN
